wzk_test_mcp/__init__.py
wzk_test_mcp/server.py
wzk_test_mcp-0.1.2.dist-info/METADATA
wzk_test_mcp-0.1.2.dist-info/WHEEL
wzk_test_mcp-0.1.2.dist-info/entry_points.txt
wzk_test_mcp-0.1.2.dist-info/RECORD
