Metadata-Version: 2.4
Name: wzk-test-mcp
Version: 0.1.2
Summary: 计算工具合集
Author-email: WB724584 <wb-wzk724584@alibaba-inc.com>
Requires-Python: >=3.10
Requires-Dist: mcp[cli]>=1.6.0
